MANIFEST.in
README.rst
setup.cfg
setup.py
behave2cucumber/__init__.py
behave2cucumber/__main__.py
behave2cucumber_lawnmowerlatte.egg-info/PKG-INFO
behave2cucumber_lawnmowerlatte.egg-info/SOURCES.txt
behave2cucumber_lawnmowerlatte.egg-info/dependency_links.txt
behave2cucumber_lawnmowerlatte.egg-info/entry_points.txt
behave2cucumber_lawnmowerlatte.egg-info/top_level.txt
tests/__init__.py
tests/test.py